pypex/__init__.py
pypex/utils.py
pypex/base/__init__.py
pypex/base/conf.py
pypex/base/shape.py
pypex/poly2d/__init__.py
pypex/poly2d/line.py
pypex/poly2d/point.py
pypex/poly2d/polygon.py
pypex/poly2d/projection.py
pypex/poly2d/intersection/__init__.py
pypex/poly2d/intersection/linter.py
pypex/poly2d/intersection/sat.py
pypex-0.2.2.dist-info/LICENSE
pypex-0.2.2.dist-info/METADATA
pypex-0.2.2.dist-info/WHEEL
pypex-0.2.2.dist-info/top_level.txt
pypex-0.2.2.dist-info/RECORD
